sherlock/__init__.py
sherlock/__main__.py
sherlock/data.py
sherlock/log.py
sherlock/service.py
sherlock/sherlockdata.py
sherlock/sherlockfinder.py
sherlock/sherlocklog.py
sherlock/sherlockservice.py
thesherlock-0.2.6.dist-info/LICENSE
thesherlock-0.2.6.dist-info/METADATA
thesherlock-0.2.6.dist-info/WHEEL
thesherlock-0.2.6.dist-info/top_level.txt
thesherlock-0.2.6.dist-info/RECORD
