Metadata-Version: 2.1
Name: thesherlock
Version: 0.2.6
Summary: Sherlock the username detective
Home-page: https://github.com/TheYahya/sherlock/
Author: 
Author-email: 
License: MIT
Keywords: sherlock finder username pypi
Platform: UNKNOWN
Classifier: Operating System :: OS Independent
Classifier: Topic :: Software Development :: Libraries :: Python Modules
Classifier: Programming Language :: Python
Classifier: Programming Language :: Python :: 3.6
Classifier: Programming Language :: Python :: 3.7
Classifier: Programming Language :: Python :: 3 :: Only
Requires-Python: >=3.5
Requires-Dist: requests
Requires-Dist: grequests
Requires-Dist: requests-futures
Requires-Dist: torrequest
Requires-Dist: colorama
